pyAllegro/__init__.py
pyAllegro/api.py
pyAllegro-0.3.1.dist-info/METADATA
pyAllegro-0.3.1.dist-info/RECORD
pyAllegro-0.3.1.dist-info/WHEEL
pyAllegro-0.3.1.dist-info/top_level.txt
