Metadata-Version: 2.1
Name: pyAllegro
Version: 0.3.1
Summary: pyAllegro is a framework, that provides a simple way to use Allegro Web API and Rest AP. 
Home-page: https://github.com/xSzpo/pyAllegro
Author: xSzpo
Author-email: xszpox@gmail.com
License: MIT
Platform: UNKNOWN
Classifier: Programming Language :: Python :: 3
Classifier: License :: OSI Approved :: MIT License
Classifier: Operating System :: OS Independent
Requires-Dist: suds-jurko
Requires-Dist: requests
